ds_base-0.1.0.dist-info/licenses/LICENSE
modules/__init__.py
modules/data.py
modules/gradient_descent.py
modules/linear_regression.py
modules/logistic_regression.py
modules/neural_network.py
ds_base-0.1.0.dist-info/METADATA
ds_base-0.1.0.dist-info/WHEEL
ds_base-0.1.0.dist-info/top_level.txt
ds_base-0.1.0.dist-info/RECORD
