Metadata-Version: 2.4
Name: ds-base
Version: 0.1.0
Summary: Some Data Since references using python pandas/numpy withOUT DEPENDENCIES
Author-email: Alexey Ivanov <asboba2101@gmail.com>
License: MIT
Requires-Python: >=3.7
License-File: LICENSE
Dynamic: license-file
